[
    {
        "host": "wx.camcard.com",
        "cnt": "1",
        "pt": "2017093002",
        "date": "20170925",
        "application_id": "105"
    },
    {
        "host": "www.yglvxingjia.com",
        "cnt": "77",
        "pt": "2017093002",
        "date": "20170925",
        "application_id": "1964"
    },
    {
        "host": "xiaobao1001.cn",
        "cnt": "4",
        "pt": "2017100823",
        "date": "20170925",
        "application_id": "2421"
    },
    {
        "host": "m.anyew.cn",
        "cnt": "1403",
        "pt": "2018010403",
        "date": "20170925",
        "application_id": "2635"
    },
    {
        "host": "www.chuangyepu.com",
        "cnt": "8",
        "pt": "2017092505",
        "date": "20170925",
        "application_id": "2677"
    },
    {
        "host": "NULL",
        "cnt": "1",
        "pt": "2017092505",
        "date": "20170925",
        "application_id": "160"
    },
    {
        "host": "service.chanjet.com",
        "cnt": "64",
        "pt": "2017092505",
        "date": "20170925",
        "application_id": "160"
    },
    {
        "host": "ar.shein.com",
        "cnt": "2",
        "pt": "2017092505",
        "date": "20170925",
        "application_id": "1826338"
    },
    {
        "host": "lijinmm.cn",
        "cnt": "1",
        "pt": "2017092505",
        "date": "20170925",
        "application_id": "2421"
    },
    {
        "host": "anyew.cn",
        "cnt": "4",
        "pt": "2017092505",
        "date": "20170925",
        "application_id": "2636"
    },
    {
        "host": "author.anyew.cn",
        "cnt": "16",
        "pt": "2017093010",
        "date": "20170925",
        "application_id": "1111"
    },
    {
        "host": "author.anyew.com",
        "cnt": "6",
        "pt": "2017093011",
        "date": "20170925",
        "application_id": "2636"
    },
    {
        "host": "www.csstock.cn",
        "cnt": "3",
        "pt": "2017092923",
        "date": "20170925",
        "application_id": "2715"
    },
    {
        "host": "activity.sudiyi.cn",
        "cnt": "1",
        "pt": "2017092505",
        "date": "20170925",
        "application_id": "3001"
    },
    {
        "host": "uniwa.cc",
        "cnt": "1",
        "pt": "2017092505",
        "date": "20170925",
        "application_id": "3039"
    },
    {
        "host": "fd.zaih.com",
        "cnt": "380",
        "pt": "2017092505",
        "date": "20170925",
        "application_id": "1285591"
    },
    {
        "host": "moni-service.chanjet.com",
        "cnt": "9",
        "pt": "2017092505",
        "date": "20170925",
        "application_id": "160"
    },
    {
        "host": "student.cd.singsound.com",
        "cnt": "1",
        "pt": "2017092505",
        "date": "20170925",
        "application_id": "171"
    },
    {
        "host": "NULL",
        "cnt": "1",
        "pt": "2017092505",
        "date": "20170925",
        "application_id": "1934"
    },
    {
        "host": "www.baidu.com",
        "cnt": "1",
        "pt": "2017092505",
        "date": "20170925",
        "application_id": "2635"
    },
    {
        "host": "NULL",
        "cnt": "1",
        "pt": "2017092505",
        "date": "20170925",
        "application_id": "2636"
    },
    {
        "host": "cichang001.com",
        "cnt": "2",
        "pt": "2017092505",
        "date": "20170925",
        "application_id": "1934"
    },
    {
        "host": "app3.qdaily.com",
        "cnt": "1",
        "pt": "2017092505",
        "date": "20170925",
        "application_id": "2262"
    },
    {
        "host": "xbx1001.cn",
        "cnt": "2",
        "pt": "2017092505",
        "date": "20170925",
        "application_id": "2421"
    },
    {
        "host": "pro.chuangyepu.com",
        "cnt": "13",
        "pt": "2017092505",
        "date": "20170925",
        "application_id": "2677"
    },
    {
        "host": "km.lexiangla.net",
        "cnt": "3",
        "pt": "2017092505",
        "date": "20170925",
        "application_id": "1239814"
    },
    {
        "host": "kakadai.kkcredit.cn",
        "cnt": "15",
        "pt": "2017092505",
        "date": "20170925",
        "application_id": "139"
    },
    {
        "host": "us.shein.com",
        "cnt": "3",
        "pt": "2017092505",
        "date": "20170925",
        "application_id": "1826338"
    },
    {
        "host": "www.geshare.com.cn",
        "cnt": "1",
        "pt": "2017092505",
        "date": "20170925",
        "application_id": "1940"
    },
    {
        "host": "bid-in.rccchina.com",
        "cnt": "784",
        "pt": "2017092505",
        "date": "20170925",
        "application_id": "2141"
    },
    {
        "host": "m.anyew.cn",
        "cnt": "1707",
        "pt": "2017092505",
        "date": "20170925",
        "application_id": "2636"
    },
    {
        "host": "abc.quesbook.com",
        "cnt": "35",
        "pt": "2017092505",
        "date": "20170925",
        "application_id": "2687"
    },
    {
        "host": "m.uniwa.cc",
        "cnt": "1",
        "pt": "2017092505",
        "date": "20170925",
        "application_id": "3039"
    },
    {
        "host": "inte-service.chanjet.com",
        "cnt": "2",
        "pt": "2017092505",
        "date": "20170925",
        "application_id": "160"
    },
    {
        "host": "NULL",
        "cnt": "1",
        "pt": "2017092505",
        "date": "20170925",
        "application_id": "1964"
    },
    {
        "host": "cure.uniqueway.com",
        "cnt": "30",
        "pt": "2017092505",
        "date": "20170925",
        "application_id": "1965"
    },
    {
        "host": "testpro2.schoolpal.cn",
        "cnt": "1",
        "pt": "2017092505",
        "date": "20170925",
        "application_id": "2341"
    },
    {
        "host": "1gai.com.cn",
        "cnt": "1",
        "pt": "2017092505",
        "date": "20170925",
        "application_id": "2421"
    },
    {
        "host": "en7nko.cn",
        "cnt": "1",
        "pt": "2017092505",
        "date": "20170925",
        "application_id": "2421"
    },
    {
        "host": "xiaobaoxiu.cn",
        "cnt": "1",
        "pt": "2017092505",
        "date": "20170925",
        "application_id": "2421"
    },
    {
        "host": "lexiangla.net",
        "cnt": "1",
        "pt": "2017092505",
        "date": "20170925",
        "application_id": "1239814"
    },
    {
        "host": "game.kkcredit.cn",
        "cnt": "110",
        "pt": "2017092505",
        "date": "20170925",
        "application_id": "139"
    },
    {
        "host": "m.sh.189.cn",
        "cnt": "9",
        "pt": "2017092505",
        "date": "20170925",
        "application_id": "157"
    },
    {
        "host": "www.shein.us",
        "cnt": "3",
        "pt": "2017092505",
        "date": "20170925",
        "application_id": "1826338"
    },
    {
        "host": "www.cichang001.com",
        "cnt": "1",
        "pt": "2017092505",
        "date": "20170925",
        "application_id": "1934"
    },
    {
        "host": "m.qdaily.com",
        "cnt": "46",
        "pt": "2017092505",
        "date": "20170925",
        "application_id": "2260"
    },
    {
        "host": "testpro.schoolpal.cn",
        "cnt": "3",
        "pt": "2017092505",
        "date": "20170925",
        "application_id": "2293"
    },
    {
        "host": "1gai.net",
        "cnt": "4",
        "pt": "2017092505",
        "date": "20170925",
        "application_id": "2421"
    },
    {
        "host": "www.anyew.cn",
        "cnt": "109",
        "pt": "2017092505",
        "date": "20170925",
        "application_id": "2636"
    },
    {
        "host": "ops.edaixi.com",
        "cnt": "1",
        "pt": "2017092505",
        "date": "20170925",
        "application_id": "382"
    },
    {
        "host": "101.201.222.217",
        "cnt": "1",
        "pt": "2017092505",
        "date": "20170925",
        "application_id": "39856"
    },
    {
        "host": "NULL",
        "cnt": "1",
        "pt": "2017092505",
        "date": "20170925",
        "application_id": "139"
    },
    {
        "host": "NULL",
        "cnt": "1",
        "pt": "2017092505",
        "date": "20170925",
        "application_id": "1826338"
    },
    {
        "host": "xiaobaoxiu01.cn",
        "cnt": "1",
        "pt": "2017092505",
        "date": "20170925",
        "application_id": "2421"
    },
    {
        "host": "NULL",
        "cnt": "1",
        "pt": "2017092505",
        "date": "20170925",
        "application_id": "2635"
    },
    {
        "host": "wx.camcard.com",
        "cnt": "1",
        "pt": "2017092505",
        "date": "20170925",
        "application_id": "107"
    },
    {
        "host": "NULL",
        "cnt": "1",
        "pt": "2017092505",
        "date": "20170925",
        "application_id": "1239814"
    },
    {
        "host": "www.makemechic.com",
        "cnt": "2",
        "pt": "2017092505",
        "date": "20170925",
        "application_id": "1765291"
    },
    {
        "host": "www.shein.com",
        "cnt": "3",
        "pt": "2017092505",
        "date": "20170925",
        "application_id": "1826338"
    },
    {
        "host": "www.uniqueway.com",
        "cnt": "32",
        "pt": "2017092505",
        "date": "20170925",
        "application_id": "1964"
    },
    {
        "host": "ms.qdaily.com",
        "cnt": "1",
        "pt": "2017092505",
        "date": "20170925",
        "application_id": "2260"
    },
    {
        "host": "pro.schoolpal.cn",
        "cnt": "7",
        "pt": "2017092505",
        "date": "20170925",
        "application_id": "2325"
    },
    {
        "host": "xbx100.cn",
        "cnt": "1",
        "pt": "2017092505",
        "date": "20170925",
        "application_id": "2421"
    },
    {
        "host": "10.11.70.41",
        "cnt": "1",
        "pt": "2017092505",
        "date": "20170925",
        "application_id": "2588"
    },
    {
        "host": "chuangyepu.com",
        "cnt": "41",
        "pt": "2017092505",
        "date": "20170925",
        "application_id": "2677"
    }
]
